swspy/__init__.py
swspy/testing.py
swspy/automate/__init__.py
swspy/automate/automation_manager.py
swspy/io/__init__.py
swspy/io/load.py
swspy/io/read_nonlinloc.py
swspy/splitting/__init__.py
swspy/splitting/forward_model.py
swspy/splitting/split.py
swspy-1.0.2.dist-info/LICENSE
swspy-1.0.2.dist-info/METADATA
swspy-1.0.2.dist-info/WHEEL
swspy-1.0.2.dist-info/top_level.txt
swspy-1.0.2.dist-info/RECORD
