Metadata-Version: 2.1
Name: swspy
Version: 1.0.2
Summary: A package for automatically calculating shear wave splitting for large earthquake catalogues.
Home-page: https://github.com/TomSHudson/swspy/
Author: Tom Hudson
Author-email: thomas.hudson@earth.ox.ac.uk
License: UNKNOWN
Platform: UNKNOWN
Classifier: Development Status :: 4 - Beta
Classifier: Programming Language :: Python :: 3
Classifier: License :: OSI Approved :: MIT License
Classifier: Operating System :: OS Independent
License-File: LICENSE
Requires-Dist: numpy
Requires-Dist: scipy
Requires-Dist: pandas
Requires-Dist: matplotlib
Requires-Dist: scikit-learn
Requires-Dist: obspy
Requires-Dist: numba
Requires-Dist: pytest
Requires-Dist: nbformat
Requires-Dist: nbconvert
Requires-Dist: ipykernel
